LICENSE
MANIFEST.in
README.rst
setup.cfg
setup.py
versioneer.py
tests/__init__.py
tests/test_general.py
tpRigToolkit/__init__.py
tpRigToolkit/tools/__init__.py
tpRigToolkit/tools/rigtoolbox/__init__.py
tpRigToolkit/tools/rigtoolbox/__logging__.ini
tpRigToolkit/tools/rigtoolbox/__version__.py
tpRigToolkit/tools/rigtoolbox/_version.py
tpRigToolkit/tools/rigtoolbox/core/__init__.py
tpRigToolkit/tools/rigtoolbox/core/client.py
tpRigToolkit/tools/rigtoolbox/core/consts.py
tpRigToolkit/tools/rigtoolbox/core/tool.py
tpRigToolkit/tools/rigtoolbox/core/toolset.py
tpRigToolkit/tools/rigtoolbox/dccs/__init__.py
tpRigToolkit/tools/rigtoolbox/dccs/maya/__init__.py
tpRigToolkit/tools/rigtoolbox/dccs/maya/server.py
tpRigToolkit/tools/rigtoolbox/dccs/maya/libs/__init__.py
tpRigToolkit/tools/rigtoolbox/dccs/maya/libs/general.py
tpRigToolkit/tools/rigtoolbox/dccs/maya/libs/joint.py
tpRigToolkit/tools/rigtoolbox/dccs/maya/libs/skin.py
tpRigToolkit/tools/rigtoolbox/dccs/maya/widgets/__init__.py
tpRigToolkit/tools/rigtoolbox/dccs/maya/widgets/control.py
tpRigToolkit/tools/rigtoolbox/dccs/maya/widgets/general.py
tpRigToolkit/tools/rigtoolbox/dccs/maya/widgets/joint.py
tpRigToolkit/tools/rigtoolbox/dccs/maya/widgets/labelsdialog.py
tpRigToolkit/tools/rigtoolbox/dccs/maya/widgets/rename.py
tpRigToolkit/tools/rigtoolbox/dccs/maya/widgets/skin.py
tpRigToolkit/tools/rigtoolbox/dccs/maya/widgets/symmesh.py
tpRigToolkit/tools/rigtoolbox/resources/icons/color/average_skin_weights.png
tpRigToolkit/tools/rigtoolbox/resources/icons/color/brSmoothWeights.png
tpRigToolkit/tools/rigtoolbox/resources/icons/color/brTransferWeights.png
tpRigToolkit/tools/rigtoolbox/resources/icons/color/center_pivot.png
tpRigToolkit/tools/rigtoolbox/resources/icons/color/clean.png
tpRigToolkit/tools/rigtoolbox/resources/icons/color/clean_skinned_mesh.png
tpRigToolkit/tools/rigtoolbox/resources/icons/color/combine_skinned_meshes.png
tpRigToolkit/tools/rigtoolbox/resources/icons/color/copy_skin_weights.png
tpRigToolkit_tools_rigtoolbox.egg-info/PKG-INFO
tpRigToolkit_tools_rigtoolbox.egg-info/SOURCES.txt
tpRigToolkit_tools_rigtoolbox.egg-info/dependency_links.txt
tpRigToolkit_tools_rigtoolbox.egg-info/not-zip-safe
tpRigToolkit_tools_rigtoolbox.egg-info/requires.txt
tpRigToolkit_tools_rigtoolbox.egg-info/top_level.txt