Metadata-Version: 2.1
Name: tpRigToolkit-tools-rigtoolbox
Version: 0.0.1
Summary: Collection of rigging tools
Home-page: https://github.com/tpRigToolkit/tpRigToolkit-tools-rigtoolbox
Author: Tomas Poveda
Author-email: tpovedatd@gmail.com
License: MIT
Platform: UNKNOWN
Provides-Extra: dev
Provides-Extra: test
